sorwave/__init__.py
sorwave/logger.py
sorwave/metadata_manager.py
sorwave/musicbrainzngs_API.py
sorwave/sorter.py
sorwave-0.0.3.dist-info/LICENSE
sorwave-0.0.3.dist-info/METADATA
sorwave-0.0.3.dist-info/WHEEL
sorwave-0.0.3.dist-info/entry_points.txt
sorwave-0.0.3.dist-info/top_level.txt
sorwave-0.0.3.dist-info/RECORD
