Metadata-Version: 2.1
Name: sorwave
Version: 0.0.3
Summary: Music Sorter based on Python
Home-page: https://github.com/a-esh/sorwave
Author: a-esh
Author-email: abrahamescalona@live.com
Classifier: Programming Language :: Python :: 3
Classifier: License :: OSI Approved :: Apache Software License
Classifier: Operating System :: OS Independent
Requires-Python: >=3.6
License-File: LICENSE
Requires-Dist: requests >=2.25.1
Requires-Dist: mutagen >=1.45.1
